clearbmk/__init__.py
clearbmk/deal_with_fps.py
clearbmk/deal_with_idfn.py
clearbmk-0.0.1.dist-info/LICENSE
clearbmk-0.0.1.dist-info/METADATA
clearbmk-0.0.1.dist-info/WHEEL
clearbmk-0.0.1.dist-info/top_level.txt
clearbmk-0.0.1.dist-info/RECORD
