Metadata-Version: 2.1
Name: clearbmk
Version: 0.0.1
Summary: 清理数据集工具箱
Home-page: https://github.com/paperplane110/clearbmk
Author: tyyuan
Author-email: 1374736649@qq.com
License: UNKNOWN
Platform: UNKNOWN
Classifier: Programming Language :: Python :: 3
Classifier: License :: OSI Approved :: MIT License
Classifier: Operating System :: OS Independent
